capl_tools_lib/__init__.py
capl_tools_lib/cli.py
capl_tools_lib/common.py
capl_tools_lib/editor.py
capl_tools_lib/elements.py
capl_tools_lib/file_manager.py
capl_tools_lib/processor.py
capl_tools_lib/scanner.py
capl_tools_lib-2.3.0.dist-info/METADATA
capl_tools_lib-2.3.0.dist-info/WHEEL
capl_tools_lib-2.3.0.dist-info/entry_points.txt
capl_tools_lib-2.3.0.dist-info/RECORD
