Metadata-Version: 2.4
Name: capl-tools-lib
Version: 2.3.0
Summary: A parser for CAPL files.
Project-URL: Homepage, https://github.com/MohamedHamed19m/CAPL_Parser
Project-URL: Repository, https://github.com/MohamedHamed19m/CAPL_Parser
Project-URL: Issues, https://github.com/MohamedHamed19m/CAPL_Parser/issues
Project-URL: Documentation, https://MohamedHamed19m.github.io/CAPL_Parser/
Author-email: Mohamed Hamed Othman <mohamedahamed1915@gmail.com>
Keywords: automotive,can,capl,parser,testing
Classifier: Development Status :: 4 - Beta
Classifier: Intended Audience :: Developers
Classifier: License :: OSI Approved :: MIT License
Classifier: Programming Language :: Python :: 3
Classifier: Programming Language :: Python :: 3.11
Classifier: Topic :: Software Development :: Libraries :: Python Modules
Requires-Python: >=3.11
Requires-Dist: python-toon>=0.1.3
Requires-Dist: rich>=13.0.0
Requires-Dist: typer>=0.12.0
